craftground/DejaVuSans-ExtraLight.ttf
craftground/initial_environment_config.py
craftground/craftground_native.pypy38-pp73-x86_64-linux-gnu.so
craftground/json_socket.py
craftground/utils.py
craftground/csv_logger.py
craftground/screen_encoding_modes.py
craftground/print_with_time.py
craftground/font.py
craftground/buffered_socket.py
craftground/__init__.py
craftground/wrappers/CleanUpFastResetWrapper.py
craftground/wrappers/fast_reset.py
craftground/wrappers/sb3_environment.py
craftground/wrappers/bimodal.py
craftground/wrappers/time_limit.py
craftground/wrappers/sound.py
craftground/wrappers/vision.py
craftground/wrappers/__init__.py
craftground/wrappers/action.py
craftground/proto/observation_space_pb2.pyi
craftground/proto/observation_space_pb2.py
craftground/proto/initial_environment_pb2.py
craftground/proto/action_space_pb2.pyi
craftground/proto/action_space_pb2.py
craftground/proto/initial_environment_pb2.pyi
craftground/environment/observation_converter.py
craftground/environment/environment.py
craftground/environment/action_space.py
craftground/environment/boost_ipc.py
craftground/environment/observation_space.py
craftground/environment/ipc_interface.py
craftground/environment/socket_ipc.py
craftground/environment/__init__.py
craftground/environments/find_village_environment.py
craftground/environments/fishing_environment.py
craftground/environments/flat_night_environment.py
craftground/environments/continuous_husks_environment.py
craftground/environments/husk_environment.py
craftground/environments/find_animal_environment.py
craftground/environments/__init__.py
craftground/environments/mansion_environment.py
craftground/environments/base_environment.py
craftground/environments/skeleton_environment.py
craftground/nbt/nbt_io.py
craftground/nbt/README.md
craftground/nbt/test_nbt.py
craftground/nbt/structure_editor.py
craftground/nbt/xml_to_nbt.py
craftground/nbt/__init__.py
craftground/nbt/NBT.md
craftground-2.6.15.dist-info/WHEEL
craftground-2.6.15.dist-info/METADATA
craftground-2.6.15.dist-info/RECORD
craftground-2.6.15.dist-info/licenses/LICENSE
