Metadata-Version: 2.2
Name: craftground
Version: 2.6.15
Summary: Lightweight Minecraft Environment for Reinforcement Learning
Keywords: minecraft,reinforcement learning,environment
License:                     GNU GENERAL PUBLIC LICENSE
Classifier: Programming Language :: Python :: 3
Classifier: License :: OSI Approved :: MIT License
Classifier: Operating System :: OS Independent
Project-URL: Source, https://github.com/yhs0602/CraftGround
Project-URL: Tracker, https://github.com/yhs0602/CraftGround/issues
Requires-Dist: gymnasium
Requires-Dist: Pillow
Requires-Dist: numpy
Requires-Dist: protobuf>=5.0.0
Requires-Dist: typing_extensions
Requires-Dist: psutil
Requires-Dist: torch
Provides-Extra: test
Requires-Dist: flake8; extra == "test"
Requires-Dist: pytest; extra == "test"
Requires-Dist: flake8-pyproject; extra == "test"
Requires-Dist: coverage; extra == "test"
Provides-Extra: jax-cuda
Requires-Dist: jax[cuda]; extra == "jax-cuda"
Provides-Extra: jax-metal
Requires-Dist: jax; extra == "jax-metal"
Requires-Dist: jax-metal; extra == "jax-metal"
